nbgitpuller_downloader_generic_web/__init__.py
nbgitpuller_downloader_generic_web/generic_web_downloader.py
nbgitpuller_downloader_generic_web-0.1.0a1.dist-info/LICENSE
nbgitpuller_downloader_generic_web-0.1.0a1.dist-info/METADATA
nbgitpuller_downloader_generic_web-0.1.0a1.dist-info/WHEEL
nbgitpuller_downloader_generic_web-0.1.0a1.dist-info/entry_points.txt
nbgitpuller_downloader_generic_web-0.1.0a1.dist-info/top_level.txt
nbgitpuller_downloader_generic_web-0.1.0a1.dist-info/RECORD
