Metadata-Version: 2.1
Name: nbgitpuller-downloader-generic-web
Version: 0.1.0a1
Summary: Downloads compressed archives from any generic webserver
Home-page: https://github.com/sean-morris/nbgitpuller-downloader-generic-web
Author: Sean Morris
Author-email: sean.smorris@berkeley.edu
License: UNKNOWN
Platform: UNKNOWN
Classifier: Programming Language :: Python :: 3
Classifier: License :: OSI Approved :: MIT License
Classifier: Operating System :: OS Independent
Requires-Python: >=3.8
License-File: LICENSE
